README.rst
setup.py
pyempt/pyempt.py
pyempt.egg-info/PKG-INFO
pyempt.egg-info/SOURCES.txt
pyempt.egg-info/dependency_links.txt
pyempt.egg-info/entry_points.txt
pyempt.egg-info/requires.txt
pyempt.egg-info/top_level.txt