Metadata-Version: 1.1
Name: pyempt
Version: 1.1.0
Summary: Python emacs syntax checking
Home-page: https://github.com/emin63/pyempt
Author: Emin Martinian
Author-email: emin.martinian@gmail.com
License: BSD
Keywords: continuous integration emacs development
Platform: UNKNOWN
Classifier: Development Status :: 3 - Alpha
Classifier: Intended Audience :: Developers
Classifier: Topic :: Software Development :: Build Tools
Classifier: License :: OSI Approved :: BSD License
Classifier: Programming Language :: Python :: 3
